xoa/__init__.py
xoa/_version.py
xoa/accessors.py
xoa/cf.ini
xoa/cf.py
xoa/cfgm.py
xoa/cli.py
xoa/color.py
xoa/coords.py
xoa/dyn.py
xoa/filter.py
xoa/geo.py
xoa/grid.py
xoa/interp.py
xoa/krig.py
xoa/misc.py
xoa/num.py
xoa/plot.py
xoa/regrid.py
xoa/sigma.py
xoa/thermdyn.py
xoa/cf_configs/__init__.py
xoa/cf_configs/argo.cfg
xoa/cf_configs/croco.cfg
xoa/cf_configs/default.cfg
xoa/cf_configs/gdp.cfg
xoa/cf_configs/hycom.cfg
xoa/cf_configs/mercator.cfg
xoa/data_samples/__init__.py
xoa/data_samples/argo-7900573.nc
xoa/data_samples/croco.south-africa.meridional.nc
xoa/data_samples/croco.south-africa.surf.nc
xoa/data_samples/croco.south-africa.zonal.nc
xoa/data_samples/gdp-6203641.csv
xoa/data_samples/hycom.gdp.h.nc
xoa/data_samples/hycom.gdp.u.nc
xoa/data_samples/hycom.gdp.v.nc
xoa/data_samples/ibi-argo-7900573.nc
xoa/tests/test_cf.py
xoa/tests/test_coords.py
xoa/tests/test_dyn.py
xoa/tests/test_filter.py
xoa/tests/test_geo.py
xoa/tests/test_grid.py
xoa/tests/test_interp.py
xoa/tests/test_misc.py
xoa/tests/test_regrid.py
xoa/tests/test_sigma.py
xoa/tests/test_thermdyn.py
xoa-0.8.0.dist-info/licenses/LICENSE
xoa-0.8.0.dist-info/METADATA
xoa-0.8.0.dist-info/WHEEL
xoa-0.8.0.dist-info/entry_points.txt
xoa-0.8.0.dist-info/top_level.txt
xoa-0.8.0.dist-info/RECORD
