Metadata-Version: 2.4
Name: xoa
Version: 0.8.0
Summary: xarray-based ocean analysis library
Author-email: Shom <stephane.raynaud@shom.fr>
License-Expression: Apache-2.0
Project-URL: homepage, https://xoa.readthedocs.io/
Project-URL: issue-tracker, https://github.com/shom-fr/xoa/issues
Project-URL: source-code, https://github.com/shom-fr/xoa
Classifier: Development Status :: 3 - Alpha
Classifier: Operating System :: OS Independent
Classifier: Intended Audience :: Science/Research
Classifier: Programming Language :: Python
Classifier: Programming Language :: Python :: 3
Classifier: Programming Language :: Python :: 3.10
Classifier: Programming Language :: Python :: 3.11
Classifier: Topic :: Scientific/Engineering
Classifier: Topic :: Scientific/Engineering :: Physics
Classifier: Topic :: Scientific/Engineering :: Atmospheric Science
Requires-Python: >=3.10
License-File: LICENSE
Requires-Dist: platformdirs
Requires-Dist: configobj
Requires-Dist: gsw
Requires-Dist: netCDF4
Requires-Dist: numba
Requires-Dist: scipy
Requires-Dist: xarray>=0.17
Provides-Extra: docs
Requires-Dist: cartopy; extra == "docs"
Requires-Dist: cmocean; extra == "docs"
Requires-Dist: ipython; extra == "docs"
Requires-Dist: jupyter_client; extra == "docs"
Requires-Dist: matplotlib; extra == "docs"
Requires-Dist: owslib; extra == "docs"
Requires-Dist: sphinx; extra == "docs"
Requires-Dist: sphinx-argparse; extra == "docs"
Requires-Dist: sphinx-book-theme; extra == "docs"
Requires-Dist: sphinxcontrib-programoutput; extra == "docs"
Requires-Dist: sphinx-gallery; extra == "docs"
Dynamic: license-file
